yitizi/__init__.py
yitizi/yitizi.json
yitizi/yitizi.py
yitizi-0.1.3.dist-info/licenses/LICENSE
yitizi-0.1.3.dist-info/METADATA
yitizi-0.1.3.dist-info/WHEEL
yitizi-0.1.3.dist-info/top_level.txt
yitizi-0.1.3.dist-info/RECORD
